asyncfifo/wptr_full.v
module wptr_full
#(
    parameter ADDRSIZE = 4
)
(
    output reg                wfull,
    output     [ADDRSIZE-1:0] waddr,
    output reg [ADDRSIZE  :0] wptr,
    input      [ADDRSIZE  :0] wq2_rptr,
    input                     wq, wclk, wrst_n
);
  reg  [ADDRSIZE:0] wbin;
  wire [ADDRSIZE:0] wgraynext, wbinnext;
  // GRAYSTYLE2 pointer
  always @(posedge wclk or negedge wrst_n) begin
      if (!wrst_n)
          {wbin, wptr} <= 0;
      else
          {wbin, wptr} <= {wbinnext, wgraynext};
  end
  // Memory write-address pointer (okay to use binary to address memory)
  assign waddr = wbin[ADDRSIZE-1:0];
  assign wbinnext  = wbin + (wq & ~wfull);
  assign wgraynext = (wbinnext>>1) ^ wbinnext; //
 
  //msb not equal msb -1 bit, and other bits are same, then full
  assign wfull_val = (wgraynext=={~wq2_rptr[ADDRSIZE:ADDRSIZE-1],wq2_rptr[ADDRSIZE-2:0]});
  always @(posedge wclk or negedge wrst_n)
      if (!wrst_n)
          wfull  <= 1'b0;
      else
          wfull  <= wfull_val;

endmodule

asyncfifo/rptr_empty.v
module rptr_empty
#(
    parameter ADDRSIZE = 4
)
(
    output reg                rempty,
    output     [ADDRSIZE-1:0] raddr, //binary ptr
    output reg [ADDRSIZE  :0] rptr,  //gray code ptr
    input      [ADDRSIZE  :0] rq2_wptr, //pointer after sync
    input                     rq, rclk, rrst_n
);
  reg  [ADDRSIZE:0] rbin;
  wire [ADDRSIZE:0] rgraynext, rbinnext;
 // GRAYSTYLE2 pointer
 // sync graycode read pointer with binary read pointer
  always @(posedge rclk or negedge rrst_n) begin
      if (!rrst_n) begin
          rbin <= 0;
          rptr <= 0;
      end
      else begin
          rbin<=rbinnext;
          rptr<=rgraynext; //output to sync_r2w.v
      end
  end
  // Memory read-address pointer (okay to use binary to address memory)
  assign raddr     = rbin[ADDRSIZE-1:0]; //
  assign rbinnext  = rbin + (rq & ~rempty); //not empty and read request, then plus 1
  assign rgraynext = (rbinnext>>1) ^ rbinnext; //graycode,左移一位异或本身得到格雷码

  // FIFO empty when the next rptr == synchronized wptr or on reset
  assign rempty_val = (rgraynext == rq2_wptr); //empty when read graycode equal write prt after sync
  always @(posedge rclk or negedge rrst_n) begin
      if (!rrst_n)
          rempty <= 1'b1;
      else
          rempty <= rempty_val;
  end
endmodule

asyncfifo/fifomem.v
module  fifomem #(parameter DATASIZE = 8,
				parameter ADDRSIZE = 4) 
	(
	 output [DATASIZE-1:0] rdata,
	 input	[DATASIZE-1:0]	wdata,
	 input	[ADDRSIZE-1:0]	waddr, raddr,
	 input					wclken, wfull, wclk
	);

	 // RTL Verilog memory model
	 localparam DEPTH = 1<<ADDRSIZE;  //depth is 2^3
	 reg [DATASIZE-1:0] mem [0:DEPTH-1];
	 assign rdata     = mem[raddr];
	 always @(posedge wclk) begin
	 if (wclken && !wfull) mem[waddr] <= wdata;
    end
endmodule

asyncfifo/sync_w2r.v
module sync_w2r
#(parameter ADDRSIZE = 4)
(
    output reg [ADDRSIZE:0] rq2_wptr, //
    input      [ADDRSIZE:0] wptr,     //
    input                   rclk, rrst_n
);

reg [ADDRSIZE:0] rq1_wptr;

  always @(posedge rclk or negedge rrst_n)
      if (!rrst_n)begin
          rq1_wptr <= 0;
          rq2_wptr <= 0;
      end
      else begin
          rq1_wptr <= wptr;
          rq2_wptr <= rq1_wptr;
      end

endmodule

asyncfifo/sync_r2w.v
module sync_r2w
#(
    parameter ADDRSIZE = 4
)
(
    output reg [ADDRSIZE:0] wq2_rptr,   //read ptr sync to write clock domain
    input      [ADDRSIZE:0] rptr,       //gray code pointer
    input                   wclk, wrst_n
);

reg [ADDRSIZE:0] wq1_rptr;

always @(posedge wclk or negedge wrst_n)
      if (!wrst_n) begin
          wq1_rptr <= 0;
          wq2_rptr <= 0;
      end
      else begin
          wq1_rptr<= rptr;
          wq2_rptr<=wq1_rptr;
      end
endmodule

asyncfifo/asyncfifo.v

module fifo_async
#(
  parameter DSIZE = 8,
  parameter ASIZE = 4
 )
 (
     input              rclk, rrst_n,rq,
     input              wclk, wrst_n,wq,
     input  [DSIZE-1:0] write_data,
     output [DSIZE-1:0] read_data,
     output             wfull,
     output             rempty
 );

  wire   [ASIZE-1:0] waddr, raddr;
  wire   [ASIZE:0]   wptr, rptr, wq2_rptr, rq2_wptr;
// synchronize the read pointer into the write-clock domain
  sync_r2w  sync_r2w
  (
                    .wq2_rptr    (wq2_rptr),
                    .rptr        (rptr    ),
                    .wclk        (wclk    ),
                    .wrst_n      (wrst_n  )
 );

// synchronize the write pointer into the read-clock domain
  sync_w2r  sync_w2r
  (
                   .rq2_wptr(rq2_wptr),
                   .wptr(wptr),
                   .rclk(rclk),
                   .rrst_n(rrst_n)
 );

//this is the FIFO memory buffer that is accessed by both the write and read clock domains.
//This buffer is most likely an instantiated, synchronous dual-port RAM.
//Other memory styles can be adapted to function as the FIFO buffer.
  fifomem
  #(DSIZE, ASIZE)
  fifomem
  (
      .rdata(read_data),
      .wdata(write_data),
      .waddr(waddr),
      .raddr(raddr),
      .wclken(wq),
      .wfull(wfull),
      .wclk(wclk)
  );

//this module is completely synchronous to the read-clock domain and contains the FIFO read pointer and empty-flag logic.
  rptr_empty
  #(ASIZE)
  rptr_empty
  (
      .rempty(rempty),
      .raddr(raddr),
      .rptr(rptr),
      .rq2_wptr(rq2_wptr),
      .rq(rq),
      .rclk(rclk),
      .rrst_n(rrst_n)
  );

//this module is completely synchronous to the write-clock domain and contains the FIFO write pointer and full-flag logic
  wptr_full
  #(ASIZE)
  wptr_full
  (
      .wfull(wfull),
      .waddr(waddr),
      .wptr(wptr),
      .wq2_rptr(wq2_rptr),
      .wq(wq),
      .wclk(wclk),
      .wrst_n(wrst_n)
  );
endmodule

asyncfifo/tb_asyncfifo.v
`include "asyncfifo.v"

module tb_asyncfifo;
reg wclk,wrst_n;
reg rclk,rrst_n;
reg wq,rq;
reg [7:0] write_data;             // data input to be pushed to buffer
wire [7:0] read_data;       // port to output the data using pop.
wire rempty,wfull;  // buffer empty and full indication

fifo_async   #(.DSIZE(8), .ASIZE(4)) fifo_inst(
	.rclk(rclk),.rrst_n(rrst_n),.rq(rq),
	.wclk(wclk),.wrst_n(wrst_n),.wq(wq),
	.write_data(write_data),.read_data(read_data),
	.wfull(wfull),.rempty(rempty));

always #10 wclk = ~wclk;
always #20 rclk = ~rclk;

reg [7:0] tempdata = 0;
    initial begin
	    rclk = 0;
	    wclk = 0;
	    #5000 $finish;
    end
    initial begin
	    wrst_n = 1;
	    #2;
	    wrst_n = 0;
	    #60;
	    wrst_n = 1;
    end

    initial begin
	    rrst_n = 1;
	    #2;
	    rrst_n = 0;
	    #120;
	    rrst_n = 1;
    end
    always  @(posedge wclk or negedge wrst_n)
    begin
	    if(wrst_n==1'b0)
	    begin
		    wq <= 0;
		    rq <= 0;
	    end
	    else begin
		    wq <= $random;
	    end
    end

    always  @(posedge rclk or negedge rrst_n)
    if(rrst_n==1'b0)
	    rq <= 0;
    else
	    rq <= $random;

   always@(*)
     if(wq == 1)
     begin
        write_data= $random ;
     end
     else
        write_data = 0;

   always @(write_data,read_data)
   begin
	$monitor($time, "write data:%d, read data:%d",write_data,read_data);
   end
	initial
	begin            
	    $dumpfile("wave.vcd");        //生成的vcd文件名称
	    $dumpvars(0, tb_asyncfifo);    //tb模块名称
	end

endmodule

asyncfifo/wave.vcd
$date
	Sun Oct 09 18:02:47 2022
$end
$version
	Icarus Verilog
$end
$timescale
	1s
$end
$scope module tb_asyncfifo $end
$var wire 1 ! wfull $end
$var wire 1 " rempty $end
$var wire 8 # read_data [7:0] $end
$var reg 1 $ rclk $end
$var reg 1 % rq $end
$var reg 1 & rrst_n $end
$var reg 8 ' tempdata [7:0] $end
$var reg 1 ( wclk $end
$var reg 1 ) wq $end
$var reg 8 * write_data [7:0] $end
$var reg 1 + wrst_n $end
$scope module fifo_inst $end
$var wire 1 $ rclk $end
$var wire 1 % rq $end
$var wire 1 & rrst_n $end
$var wire 1 ( wclk $end
$var wire 1 ) wq $end
$var wire 8 , write_data [7:0] $end
$var wire 1 + wrst_n $end
$var wire 5 - wq2_rptr [4:0] $end
$var wire 5 . wptr [4:0] $end
$var wire 1 ! wfull $end
$var wire 4 / waddr [3:0] $end
$var wire 5 0 rq2_wptr [4:0] $end
$var wire 5 1 rptr [4:0] $end
$var wire 1 " rempty $end
$var wire 8 2 read_data [7:0] $end
$var wire 4 3 raddr [3:0] $end
$var parameter 32 4 ASIZE $end
$var parameter 32 5 DSIZE $end
$scope module fifomem $end
$var wire 8 6 rdata [7:0] $end
$var wire 1 ( wclk $end
$var wire 1 ) wclken $end
$var wire 8 7 wdata [7:0] $end
$var wire 1 ! wfull $end
$var wire 4 8 waddr [3:0] $end
$var wire 4 9 raddr [3:0] $end
$var parameter 32 : ADDRSIZE $end
$var parameter 32 ; DATASIZE $end
$var parameter 36 < DEPTH $end
$upscope $end
$scope module rptr_empty $end
$var wire 1 $ rclk $end
$var wire 5 = rgraynext [4:0] $end
$var wire 1 % rq $end
$var wire 1 & rrst_n $end
$var wire 5 > rq2_wptr [4:0] $end
$var wire 1 ? rempty_val $end
$var wire 5 @ rbinnext [4:0] $end
$var wire 4 A raddr [3:0] $end
$var parameter 32 B ADDRSIZE $end
$var reg 5 C rbin [4:0] $end
$var reg 1 " rempty $end
$var reg 5 D rptr [4:0] $end
$upscope $end
$scope module sync_r2w $end
$var wire 5 E rptr [4:0] $end
$var wire 1 ( wclk $end
$var wire 1 + wrst_n $end
$var parameter 32 F ADDRSIZE $end
$var reg 5 G wq1_rptr [4:0] $end
$var reg 5 H wq2_rptr [4:0] $end
$upscope $end
$scope module sync_w2r $end
$var wire 1 $ rclk $end
$var wire 1 & rrst_n $end
$var wire 5 I wptr [4:0] $end
$var parameter 32 J ADDRSIZE $end
$var reg 5 K rq1_wptr [4:0] $end
$var reg 5 L rq2_wptr [4:0] $end
$upscope $end
$scope module wptr_full $end
$var wire 1 ( wclk $end
$var wire 5 M wgraynext [4:0] $end
$var wire 1 ) wq $end
$var wire 5 N wq2_rptr [4:0] $end
$var wire 1 + wrst_n $end
$var wire 1 O wfull_val $end
$var wire 5 P wbinnext [4:0] $end
$var wire 4 Q waddr [3:0] $end
$var parameter 32 R ADDRSIZE $end
$var reg 5 S wbin [4:0] $end
$var reg 1 ! wfull $end
$var reg 5 T wptr [4:0] $end
$upscope $end
$upscope $end
$upscope $end
$enddefinitions $end
$comment Show the parameter values. $end
$dumpall
b100 R
b100 J
b100 F
b100 B
b10000 <
b1000 ;
b100 :
b1000 5
b100 4
$end
#0
$dumpvars
bx T
bx S
bx Q
bx P
xO
bx N
bx M
bx L
bx K
bx I
bx H
bx G
bx E
bx D
bx C
bx A
bx @
x?
bx >
bx =
bx 9
bx 8
bx 7
bx 6
bx 3
bx 2
bx 1
bx 0
bx /
bx .
bx -
bx ,
1+
bx *
x)
0(
b0 '
1&
x%
0$
bx #
x"
x!
$end
#2
1?
0O
b0 =
b0 M
b0 3
b0 9
b0 A
b0 /
b0 8
b0 Q
b0 @
b0 P
b0 *
b0 ,
b0 7
b0 0
b0 >
b0 L
b0 K
b0 1
b0 D
b0 E
b0 C
1"
b0 -
b0 H
b0 N
b0 G
b0 S
b0 .
b0 I
b0 T
0!
0%
0)
0&
0+
#10
1(
#20
0(
1$
#30
1(
#40
0(
0$
#50
1(
#60
0(
1$
#62
1+
#70
1(
#80
0(
0$
#90
b1 M
b1 P
b1001 *
b1001 ,
b1001 7
1)
1(
#100
0(
1$
#110
b1 /
b1 8
b1 Q
b11 M
b1001 #
b1001 2
b1001 6
b10 P
b1 S
b1 .
b1 I
b1 T
1(
#120
0(
0$
#122
1&
#130
b10 /
b10 8
b10 Q
b10 M
b11 P
b10 S
b11 .
b11 I
b11 T
1(
#140
b11 K
1%
0(
1$
#150
b11 /
b11 8
b11 Q
b110 M
b100 P
b11 S
b10 .
b10 I
b10 T
1(
#160
0(
0$
#170
b0 *
b0 ,
b0 7
b100 /
b100 8
b100 Q
b110 M
0)
b100 P
b100 S
b110 .
b110 I
b110 T
1(
#180
0?
b11 0
b11 >
b11 L
b110 K
0(
1$
#190
b111 M
b101 P
b1110110 *
b1110110 ,
b1110110 7
1)
1(
#200
0(
0$
#210
b101 /
b101 8
b101 Q
b101 M
b110 P
b101 S
b111 .
b111 I
b111 T
1(
#220
b1 =
b1 @
b110 0
b110 >
b110 L
b111 K
0"
0(
1$
#230
b110 /
b110 8
b110 Q
b0 *
b0 ,
b0 7
b110 P
b110 S
b101 .
b101 I
b101 T
0)
1(
#240
0(
0$
#250
b100 M
b111 P
b11000110 *
b11000110 ,
b11000110 7
1)
1(
#260
b1 3
b1 9
b1 A
b11 =
b1 1
b1 D
b1 E
b10 @
b1 C
b111 0
b111 >
b111 L
b101 K
0(
1$
#270
b111 /
b111 8
b111 Q
b0 *
b0 ,
b0 7
b1 G
b111 P
b111 S
b100 .
b100 I
b100 T
0)
1(
#280
0(
0$
#290
b1100 M
b1000 P
b1110111 *
b1110111 ,
b1110111 7
1)
b1 -
b1 H
b1 N
1(
#300
b10 3
b10 9
b10 A
b101 0
b101 >
b101 L
b100 K
b11 1
b11 D
b11 E
b10 @
b10 C
0%
0(
1$
#310
b1000 /
b1000 8
b1000 Q
b1101 M
b11 G
b1001 P
b1000 S
b1100 .
b1100 I
b1100 T
1(
#320
0(
0$
#330
b0 *
b0 ,
b0 7
b1001 /
b1001 8
b1001 Q
b1101 M
0)
b1001 P
b1001 S
b1101 .
b1101 I
b1101 T
b11 -
b11 H
b11 N
1(
#340
b100 0
b100 >
b100 L
b1101 K
0(
1$
#350
1(
#360
0(
0$
#370
b1111 M
b1010 P
b1011100 *
b1011100 ,
b1011100 7
1)
1(
#380
b10 =
b11 @
b1101 0
b1101 >
b1101 L
1%
0(
1$
#390
b1010 /
b1010 8
b1010 Q
b1110 M
b1011 P
b1010 S
b1111 .
b1111 I
b1111 T
1(
#400
0(
0$
#410
b1011 /
b1011 8
b1011 Q
b1010 M
b1100 P
b1011 S
b1110 .
b1110 I
b1110 T
1(
#420
b11 3
b11 9
b11 A
b110 =
b10 1
b10 D
b10 E
b100 @
b11 C
b1110 K
0(
1$
#430
b1100 /
b1100 8
b1100 Q
b0 *
b0 ,
b0 7
b10 G
b1100 P
b1100 S
b1010 .
b1010 I
b1010 T
0)
1(
#440
0(
0$
#450
b10 -
b10 H
b10 N
1(
#460
b1110110 #
b1110110 2
b1110110 6
b100 3
b100 9
b100 A
b1110 0
b1110 >
b1110 L
b1010 K
b110 1
b110 D
b110 E
b100 @
b100 C
0%
0(
1$
#470
b110 G
1(
#480
0(
0$
#490
b1011 M
b1101 P
b10010110 *
b10010110 ,
b10010110 7
1)
b110 -
b110 H
b110 N
1(
#500
b111 =
b101 @
1%
b1010 0
b1010 >
b1010 L
0(
1$
#510
b1101 /
b1101 8
b1101 Q
b1001 M
b1110 P
b1101 S
b1011 .
b1011 I
b1011 T
1(
#520
0(
0$
#530
b1110 /
b1110 8
b1110 Q
b1000 M
b1111 P
b1110 S
b1001 .
b1001 I
b1001 T
1(
#540
b101 3
b101 9
b101 A
b101 =
b1001 K
b111 1
b111 D
b111 E
b110 @
b101 C
0(
1$
#550
b1111 /
b1111 8
b1111 Q
b11000 M
b111 G
b10000 P
b1111 S
b1000 .
b1000 I
b1000 T
1(
#560
0(
0$
#570
b0 *
b0 ,
b0 7
b0 /
b0 8
b0 Q
b11000 M
0)
b10000 P
b10000 S
b11000 .
b11000 I
b11000 T
b111 -
b111 H
b111 N
1(
#580
b11000110 #
b11000110 2
b11000110 6
b110 3
b110 9
b110 A
b101 =
0%
b101 1
b101 D
b101 E
b110 @
b110 C
b1001 0
b1001 >
b1001 L
b11000 K
0(
1$
#590
b11001 M
b10001 P
b11001111 *
b11001111 ,
b11001111 7
b101 G
1)
1(
#600
0(
0$
#610
b1 /
b1 8
b1 Q
b11011 M
b10010 P
b10001 S
b11001 .
b11001 I
b11001 T
b101 -
b101 H
b101 N
1(
#620
b11000 0
b11000 >
b11000 L
b11001 K
0(
1$
#630
b10 /
b10 8
b10 Q
b0 *
b0 ,
b0 7
b10010 P
b10010 S
b11011 .
b11011 I
b11011 T
0)
1(
#640
0(
0$
#650
1(
#660
b11001 0
b11001 >
b11001 L
b11011 K
0(
1$
#670
1(
#680
0(
0$
#690
b11010 M
b10011 P
b11011000 *
b11011000 ,
b11011000 7
1)
1(
#700
b11011 0
b11011 >
b11011 L
0(
1$
#710
b11 /
b11 8
b11 Q
0O
b11110 M
b10100 P
b10011 S
b11010 .
b11010 I
b11010 T
1(
#720
0(
0$
#730
b100 /
b100 8
b100 Q
b11111 M
b10101 P
b10100 S
b11110 .
b11110 I
b11110 T
1(
#740
b11110 K
0(
1$
#750
b101 /
b101 8
b101 Q
b0 *
b0 ,
b0 7
b10101 P
b10101 S
b11111 .
b11111 I
b11111 T
0)
1(
#760
0(
0$
#770
1(
#780
b11110 0
b11110 >
b11110 L
b11111 K
0(
1$
#790
1(
#800
0(
0$
#810
1O
b11101 M
b10110 P
b1110001 *
b1110001 ,
b1110001 7
1)
1(
#820
b100 =
b111 @
1%
b11111 0
b11111 >
b11111 L
0(
1$
#830
b110 /
b110 8
b110 Q
1O
b11101 M
b10110 P
b10110 S
b11101 .
b11101 I
b11101 T
1!
1(
#840
0(
0$
#850
1(
#860
b1110111 #
b1110111 2
b1110111 6
b111 3
b111 9
b111 A
b11101 K
b100 1
b100 D
b100 E
b111 @
b111 C
0%
0(
1$
#870
b0 *
b0 ,
b0 7
b100 G
0)
1(
#880
0(
0$
#890
b11110001 *
b11110001 ,
b11110001 7
0O
1)
b100 -
b100 H
b100 N
1(
#900
b1100 =
b1000 @
1%
b11101 0
b11101 >
b11101 L
0(
1$
#910
b0 *
b0 ,
b0 7
0!
0)
1(
#920
0(
0$
#930
1(
#940
b1000 3
b1000 9
b1000 A
b1101 =
b1100 1
b1100 D
b1100 E
b1001 @
b1000 C
0(
1$
#950
1O
b11100 M
b10111 P
b11111000 *
b11111000 ,
b11111000 7
b1100 G
1)
1(
#960
0(
0$
#970
b111 /
b111 8
b111 Q
0O
b11100 M
1!
b10111 P
b10111 S
b11100 .
b11100 I
b11100 T
b1100 -
b1100 H
b1100 N
1(
#980
b1011100 #
b1011100 2
b1011100 6
b1001 3
b1001 9
b1001 A
b1111 =
b1101 1
b1101 D
b1101 E
b1010 @
b1001 C
b11100 K
0(
1$
#990
b0 *
b0 ,
b0 7
b1101 G
0!
0)
1(
#1000
0(
0$
#1010
b10100 M
b11000 P
b10001001 *
b10001001 ,
b10001001 7
1)
b1101 -
b1101 H
b1101 N
1(
#1020
b1010 3
b1010 9
b1010 A
b1110 =
b11100 0
b11100 >
b11100 L
b1111 1
b1111 D
b1111 E
b1011 @
b1010 C
0(
1$
#1030
b1000 /
b1000 8
b1000 Q
b0 *
b0 ,
b0 7
b1111 G
b11000 P
b11000 S
b10100 .
b10100 I
b10100 T
0)
1(
#1040
0(
0$
#1050
b10101 M
b11001 P
b1010001 *
b1010001 ,
b1010001 7
1)
b1111 -
b1111 H
b1111 N
1(
#1060
b1011 3
b1011 9
b1011 A
b1110 =
0%
b1110 1
b1110 D
b1110 E
b1011 @
b1011 C
b10100 K
0(
1$
#1070
b1001 /
b1001 8
b1001 Q
b0 *
b0 ,
b0 7
b1110 G
b11001 P
b11001 S
b10101 .
b10101 I
b10101 T
0)
1(
#1080
0(
0$
#1090
b1110 -
b1110 H
b1110 N
1(
#1100
b10100 0
b10100 >
b10100 L
b10101 K
0(
1$
#1110
0O
b10111 M
b11010 P
b111101 *
b111101 ,
b111101 7
1)
1(
#1120
0(
0$
#1130
b0 *
b0 ,
b0 7
b1010 /
b1010 8
b1010 Q
0O
b10111 M
0)
b11010 P
b11010 S
b10111 .
b10111 I
b10111 T
1(
#1140
b10101 0
b10101 >
b10101 L
b10111 K
0(
1$
#1150
1O
b10110 M
b11011 P
b111001 *
b111001 ,
b111001 7
1)
1(
#1160
0(
0$
#1170
b1011 /
b1011 8
b1011 Q
1O
b10110 M
1!
b11011 P
b11011 S
b10110 .
b10110 I
b10110 T
1(
#1180
b1010 =
b1100 @
b10111 0
b10111 >
b10111 L
b10110 K
1%
0(
1$
#1190
1(
#1200
0(
0$
#1210
b0 *
b0 ,
b0 7
0)
1(
#1220
b10010110 #
b10010110 2
b10010110 6
b1100 3
b1100 9
b1100 A
b1011 =
b1010 1
b1010 D
b1010 E
b1101 @
b1100 C
b10110 0
b10110 >
b10110 L
0(
1$
#1230
b111111 *
b111111 ,
b111111 7
b1010 G
1)
1(
#1240
0(
0$
#1250
b0 *
b0 ,
b0 7
0O
0)
b1010 -
b1010 H
b1010 N
1(
#1260
b1101 3
b1101 9
b1101 A
b1011 1
b1011 D
b1011 E
b1101 @
b1101 C
0%
0(
1$
#1270
b1011 G
0!
1(
#1280
0(
0$
#1290
b1011 -
b1011 H
b1011 N
1(
#1300
0(
1$
#1310
1(
#1320
0(
0$
#1330
1(
#1340
b1001 =
b1110 @
1%
0(
1$
#1350
b10010 M
b11100 P
b101111 *
b101111 ,
b101111 7
1)
1(
#1360
0(
0$
#1370
b1100 /
b1100 8
b1100 Q
1O
b10011 M
b11101 P
b11100 S
b10010 .
b10010 I
b10010 T
1(
#1380
b1110 3
b1110 9
b1110 A
b1000 =
b1001 1
b1001 D
b1001 E
b1111 @
b1110 C
b10010 K
0(
1$
#1390
b1101 /
b1101 8
b1101 Q
b0 *
b0 ,
b0 7
b1001 G
b11101 P
b11101 S
b10011 .
b10011 I
b10011 T
1!
0)
1(
#1400
0(
0$
#1410
b11001011 *
b11001011 ,
b11001011 7
0O
1)
b1001 -
b1001 H
b1001 N
1(
#1420
b1111 3
b1111 9
b1111 A
b10010 0
b10010 >
b10010 L
b10011 K
b1000 1
b1000 D
b1000 E
b1111 @
b1111 C
0%
0(
1$
#1430
b0 *
b0 ,
b0 7
b1000 G
0!
0)
1(
#1440
0(
0$
#1450
0O
b10001 M
b11110 P
b11101101 *
b11101101 ,
b11101101 7
1)
b1000 -
b1000 H
b1000 N
1(
#1460
b10011 0
b10011 >
b10011 L
0(
1$
#1470
b1110 /
b1110 8
b1110 Q
1O
b10000 M
b11111 P
b11110 S
b10001 .
b10001 I
b10001 T
1(
#1480
0(
0$
#1490
b1111 /
b1111 8
b1111 Q
1O
b10000 M
1!
b11111 P
b11111 S
b10000 .
b10000 I
b10000 T
1(
#1500
b11000 =
b10000 @
b10000 K
1%
0(
1$
#1510
1(
#1520
0(
0$
#1530
b0 *
b0 ,
b0 7
0)
1(
#1540
b11001111 #
b11001111 2
b11001111 6
b0 3
b0 9
b0 A
b11000 =
0%
b11000 1
b11000 D
b11000 E
b10000 @
b10000 C
b10000 0
b10000 >
b10000 L
0(
1$
#1550
b11000 G
1(
#1560
0(
0$
#1570
0O
b1110 *
b1110 ,
b1110 7
1)
b11000 -
b11000 H
b11000 N
1(
#1580
0(
1$
#1590
b0 *
b0 ,
b0 7
0!
0)
1(
#1600
0(
0$
#1610
1O
b0 M
b0 P
b11000011 *
b11000011 ,
b11000011 7
1)
1(
#1620
0(
1$
#1630
b0 /
b0 8
b0 Q
b0 *
b0 ,
b0 7
b0 P
b0 S
b0 .
b0 I
b0 T
1!
0)
1(
#1640
0(
0$
#1650
b1010 *
b1010 ,
b1010 7
1)
1(
#1660
b0 K
0(
1$
#1670
b0 *
b0 ,
b0 7
0)
1(
#1680
0(
0$
#1690
b10111000 *
b10111000 ,
b10111000 7
1)
1(
#1700
b0 0
b0 >
b0 L
0(
1$
#1710
1(
#1720
0(
0$
#1730
b0 *
b0 ,
b0 7
0)
1(
#1740
b11001 =
b10001 @
1%
0(
1$
#1750
b1001101 *
b1001101 ,
b1001101 7
1)
1(
#1760
0(
0$
#1770
1(
#1780
b1 3
b1 9
b1 A
b11011 =
b11001 1
b11001 D
b11001 E
b10010 @
b10001 C
0(
1$
#1790
b0 *
b0 ,
b0 7
b11001 G
0)
1(
#1800
0(
0$
#1810
0O
b11001 -
b11001 H
b11001 N
1(
#1820
b11011000 #
b11011000 2
b11011000 6
b10 3
b10 9
b10 A
b11011 1
b11011 D
b11011 E
b10010 @
b10010 C
0%
0(
1$
#1830
1O
b1 M
b1 P
b1000110 *
b1000110 ,
b1000110 7
b11011 G
0!
1)
1(
#1840
0(
0$
#1850
b0 *
b0 ,
b0 7
b1 /
b1 8
b1 Q
b1 M
0O
0)
1!
b1 P
b1 S
b1 .
b1 I
b1 T
b11011 -
b11011 H
b11011 N
1(
#1860
b11010 =
b10011 @
1%
b1 K
0(
1$
#1870
1O
b11 M
b10 P
b10110100 *
b10110100 ,
b10110100 7
0!
1)
1(
#1880
0(
0$
#1890
b0 *
b0 ,
b0 7
b10 /
b10 8
b10 Q
1O
b11 M
0)
1!
b10 P
b10 S
b11 .
b11 I
b11 T
1(
#1900
b11 3
b11 9
b11 A
b1 0
b1 >
b1 L
b11 K
b11010 1
b11010 D
b11010 E
b10011 @
b10011 C
0%
0(
1$
#1910
b11000111 *
b11000111 ,
b11000111 7
b11010 G
1)
1(
#1920
0(
0$
#1930
b0 *
b0 ,
b0 7
0O
0)
b11010 -
b11010 H
b11010 N
1(
#1940
b11 0
b11 >
b11 L
0(
1$
#1950
0!
1(
#1960
0(
0$
#1970
1O
b10 M
b11 P
b101001 *
b101001 ,
b101001 7
1)
1(
#1980
0(
1$
#1990
b11 /
b11 8
b11 Q
b0 *
b0 ,
b0 7
b11 P
b11 S
b10 .
b10 I
b10 T
1!
0)
1(
#2000
0(
0$
#2010
1(
#2020
b11110 =
b10100 @
1%
b10 K
0(
1$
#2030
1(
#2040
0(
0$
#2050
1(
#2060
b100 3
b100 9
b100 A
b11111 =
b10 0
b10 >
b10 L
b11110 1
b11110 D
b11110 E
b10101 @
b10100 C
0(
1$
#2070
b11110 G
1(
#2080
0(
0$
#2090
0O
b11110 -
b11110 H
b11110 N
1(
#2100
b1110001 #
b1110001 2
b1110001 6
b101 3
b101 9
b101 A
b11111 =
0%
b11111 1
b11111 D
b11111 E
b10101 @
b10101 C
0(
1$
#2110
1O
b110 M
b100 P
b11010 *
b11010 ,
b11010 7
b11111 G
0!
1)
1(
#2120
0(
0$
#2130
b100 /
b100 8
b100 Q
b110 M
0O
1!
b100 P
b100 S
b110 .
b110 I
b110 T
b11111 -
b11111 H
b11111 N
1(
#2140
b11101 =
b10110 @
b110 K
1%
0(
1$
#2150
b0 *
b0 ,
b0 7
0!
0)
1(
#2160
0(
0$
#2170
1(
#2180
b11111000 #
b11111000 2
b11111000 6
b110 3
b110 9
b110 A
b11101 =
0%
b11101 1
b11101 D
b11101 E
b10110 @
b10110 C
b110 0
b110 >
b110 L
0(
1$
#2190
b11101 G
1(
#2200
0(
0$
#2210
b111 M
b101 P
b11011100 *
b11011100 ,
b11011100 7
1)
b11101 -
b11101 H
b11101 N
1(
#2220
0(
1$
#2230
b101 /
b101 8
b101 Q
b0 *
b0 ,
b0 7
b101 P
b101 S
b111 .
b111 I
b111 T
0)
1(
#2240
0(
0$
#2250
1(
#2260
b11100 =
b10111 @
1%
b111 K
0(
1$
#2270
1O
b101 M
b110 P
b1111001 *
b1111001 ,
b1111001 7
1)
1(
#2280
0(
0$
#2290
b0 *
b0 ,
b0 7
b110 /
b110 8
b110 Q
1O
b101 M
0)
1!
b110 P
b110 S
b101 .
b101 I
b101 T
1(
#2300
b10001001 #
b10001001 2
b10001001 6
b111 3
b111 9
b111 A
b10100 =
b111 0
b111 >
b111 L
b101 K
b11100 1
b11100 D
b11100 E
b11000 @
b10111 C
0(
1$
#2310
b10100001 *
b10100001 ,
b10100001 7
b11100 G
1)
1(
#2320
0(
0$
#2330
b0 *
b0 ,
b0 7
0O
0)
b11100 -
b11100 H
b11100 N
1(
#2340
b1010001 #
b1010001 2
b1010001 6
b1000 3
b1000 9
b1000 A
b10100 =
0%
b10100 1
b10100 D
b10100 E
b11000 @
b11000 C
b101 0
b101 >
b101 L
0(
1$
#2350
1O
b100 M
b111 P
b110101 *
b110101 ,
b110101 7
b10100 G
0!
1)
1(
#2360
0(
0$
#2370
b111 /
b111 8
b111 Q
0O
b100 M
1!
b111 P
b111 S
b100 .
b100 I
b100 T
b10100 -
b10100 H
b10100 N
1(
#2380
b10101 =
b11001 @
b100 K
1%
0(
1$
#2390
1O
b1100 M
b1000 P
0!
1(
#2400
0(
0$
#2410
b0 *
b0 ,
b0 7
b1000 /
b1000 8
b1000 Q
1O
b1100 M
0)
1!
b1000 P
b1000 S
b1100 .
b1100 I
b1100 T
1(
#2420
b111101 #
b111101 2
b111101 6
b1001 3
b1001 9
b1001 A
b10111 =
b10101 1
b10101 D
b10101 E
b11010 @
b11001 C
b100 0
b100 >
b100 L
b1100 K
0(
1$
#2430
b11101100 *
b11101100 ,
b11101100 7
b10101 G
1)
1(
#2440
0(
0$
#2450
b0 *
b0 ,
b0 7
0O
0)
b10101 -
b10101 H
b10101 N
1(
#2460
b111001 #
b111001 2
b111001 6
b1010 3
b1010 9
b1010 A
b1100 0
b1100 >
b1100 L
b10111 1
b10111 D
b10111 E
b11010 @
b11010 C
0%
0(
1$
#2470
b10111 G
0!
1(
#2480
0(
0$
#2490
b1101 M
b1001 P
b10100001 *
b10100001 ,
b10100001 7
1)
b10111 -
b10111 H
b10111 N
1(
#2500
0(
1$
#2510
b1001 /
b1001 8
b1001 Q
b0 *
b0 ,
b0 7
b1001 P
b1001 S
b1101 .
b1101 I
b1101 T
0)
1(
#2520
0(
0$
#2530
1O
b1111 M
b1010 P
b101010 *
b101010 ,
b101010 7
1)
1(
#2540
b1101 K
0(
1$
